gemfileparser.py
gemfileparser2.py
gemfileparser2-0.9.4.dist-info/LICENSE.GPLv3
gemfileparser2-0.9.4.dist-info/LICENSE.MIT
gemfileparser2-0.9.4.dist-info/METADATA
gemfileparser2-0.9.4.dist-info/README.rst
gemfileparser2-0.9.4.dist-info/WHEEL
gemfileparser2-0.9.4.dist-info/top_level.txt
gemfileparser2-0.9.4.dist-info/RECORD
