Metadata-Version: 2.1
Name: gemfileparser2
Version: 0.9.4
Summary: Parse Ruby Gemfile, .gemspec and Cocoapod .podspec files using Python.
Home-page: https://github.com/aboutcode-org/gemfileparser2
Author: Balasankar C, Rohit Potter, nexB. Inc. and others
Author-email: info@aboutcode.org
License: GPL-3.0-or-later OR MIT
Keywords: Ruby Rubygem Gemfile gemspec Cocoapod podspec
Classifier: Development Status :: 5 - Production/Stable
Classifier: Intended Audience :: Developers
Classifier: Operating System :: OS Independent
Classifier: Programming Language :: Python :: 3
Classifier: Programming Language :: Python :: 3 :: Only
Classifier: Topic :: Software Development
Classifier: Topic :: Utilities
Requires-Python: >=3.7
License-File: README.rst
License-File: LICENSE.GPLv3
License-File: LICENSE.MIT
Provides-Extra: docs
Requires-Dist: Sphinx>=5.0.2; extra == "docs"
Requires-Dist: sphinx-rtd-theme>=1.0.0; extra == "docs"
Requires-Dist: sphinx-reredirects>=0.1.2; extra == "docs"
Requires-Dist: doc8>=0.11.2; extra == "docs"
Provides-Extra: testing
Requires-Dist: pytest!=7.0.0,>=6; extra == "testing"
Requires-Dist: pytest-xdist>=2; extra == "testing"
Requires-Dist: aboutcode-toolkit>=7.0.2; extra == "testing"
Requires-Dist: pycodestyle>=2.8.0; extra == "testing"
Requires-Dist: twine; extra == "testing"
Requires-Dist: black; extra == "testing"
Requires-Dist: isort; extra == "testing"
